fixie_proto/__init__.py
fixie_proto/fixie/__init__.py
fixie_proto/fixie/corpora/__init__.py
fixie_proto/fixie/corpora/v1/__init__.py
fixie_proto/fixie/corpora/v1/common_pb2.py
fixie_proto/fixie/corpora/v1/common_pb2.pyi
fixie_proto/fixie/corpora/v1/loader_pb2.py
fixie_proto/fixie/corpora/v1/loader_pb2.pyi
fixie_proto-0.1.3.dist-info/METADATA
fixie_proto-0.1.3.dist-info/WHEEL
fixie_proto-0.1.3.dist-info/RECORD
